deprecated_parameters/__init__.py
deprecated_parameters/_decorator.py
deprecated_parameters/_mypy.py
deprecated_parameters/py.typed
deprecated_parameters_tests/__main__.py
deprecated_parameters_tests/test_decorator.py
deprecated_parameters-0.1.0.dev2.dist-info/LICENSE.rst
deprecated_parameters-0.1.0.dev2.dist-info/METADATA
deprecated_parameters-0.1.0.dev2.dist-info/WHEEL
deprecated_parameters-0.1.0.dev2.dist-info/top_level.txt
deprecated_parameters-0.1.0.dev2.dist-info/RECORD
