Metadata-Version: 2.2
Name: deprecated-parameters
Version: 0.1.0.dev2
Summary: Deprecation of parameters in function and method signatures.
Author-email: Mauricio Villegas <mauricio@omnius.com>
License: The MIT License (MIT)
Project-URL: GitHub, https://github.com/mauvilsa/deprecated-parameters
Project-URL: PyPI, https://pypi.org/project/deprecated-parameters
Platform: Any
Classifier: Development Status :: 1 - Planning
Classifier: Programming Language :: Python
Classifier: Programming Language :: Python :: 3
Classifier: Programming Language :: Python :: 3 :: Only
Classifier: Programming Language :: Python :: 3.8
Classifier: Programming Language :: Python :: 3.9
Classifier: Programming Language :: Python :: 3.10
Classifier: Programming Language :: Python :: 3.11
Classifier: Programming Language :: Python :: 3.12
Classifier: Programming Language :: Python :: 3.13
Classifier: Intended Audience :: Developers
Classifier: License :: OSI Approved :: MIT License
Classifier: Operating System :: POSIX :: Linux
Classifier: Operating System :: MacOS
Classifier: Operating System :: Microsoft :: Windows
Requires-Python: >=3.8
License-File: LICENSE.rst
Provides-Extra: mypy
Requires-Dist: mypy>=1.15.0; extra == "mypy"
Provides-Extra: test
Requires-Dist: pytest>=6.2.5; extra == "test"
Requires-Dist: pytest-cov>=4.0.0; extra == "test"
Provides-Extra: dev
Requires-Dist: pre-commit>=2.19.0; extra == "dev"
Requires-Dist: tox>=3.25.0; extra == "dev"
Requires-Dist: build>=0.10.0; extra == "dev"
